TiwenDeZhihui/README.md
TiwenDeZhihui/__init__.py
TiwenDeZhihui/__main__.py
TiwenDeZhihui/file.epub
TiwenDeZhihui/index.html
TiwenDeZhihui/css/__init__.py
TiwenDeZhihui/css/annotations.css
TiwenDeZhihui/css/main.css
TiwenDeZhihui/css/normalize.css
TiwenDeZhihui/css/popup.css
TiwenDeZhihui/font/__init__.py
TiwenDeZhihui/font/fontello.eot
TiwenDeZhihui/font/fontello.svg
TiwenDeZhihui/font/fontello.ttf
TiwenDeZhihui/font/fontello.woff
TiwenDeZhihui/img/__init__.py
TiwenDeZhihui/img/annotator-glyph-sprite.png
TiwenDeZhihui/img/annotator-icon-sprite.png
TiwenDeZhihui/img/apple-touch-icon.png
TiwenDeZhihui/img/cancelfullscreen.png
TiwenDeZhihui/img/close.png
TiwenDeZhihui/img/fullscreen.png
TiwenDeZhihui/img/loader.gif
TiwenDeZhihui/img/menu-icon.png
TiwenDeZhihui/img/save.png
TiwenDeZhihui/img/saved.png
TiwenDeZhihui/img/settings-s.png
TiwenDeZhihui/img/settings.png
TiwenDeZhihui/img/star.png
TiwenDeZhihui/js/__init__.py
TiwenDeZhihui/js/epub.js
TiwenDeZhihui/js/epub.min.js
TiwenDeZhihui/js/epub.min.map
TiwenDeZhihui/js/hooks.min.js
TiwenDeZhihui/js/hooks.min.map
TiwenDeZhihui/js/reader.js
TiwenDeZhihui/js/reader.js.map
TiwenDeZhihui/js/reader.min.js
TiwenDeZhihui/js/reader.min.map
TiwenDeZhihui/js/hooks/__init__.py
TiwenDeZhihui/js/hooks/extensions/__init__.py
TiwenDeZhihui/js/hooks/extensions/highlight.js
TiwenDeZhihui/js/libs/__init__.py
TiwenDeZhihui/js/libs/jquery.min.js
TiwenDeZhihui/js/libs/localforage.min.js
TiwenDeZhihui/js/libs/screenfull.js
TiwenDeZhihui/js/libs/screenfull.min.js
TiwenDeZhihui/js/libs/zip.min.js
TiwenDeZhihui/js/plugins/__init__.py
TiwenDeZhihui/js/plugins/hypothesis.js
TiwenDeZhihui/js/plugins/search.js
tiwen_de_zhihui-2024.3.2.0.dist-info/METADATA
tiwen_de_zhihui-2024.3.2.0.dist-info/WHEEL
tiwen_de_zhihui-2024.3.2.0.dist-info/entry_points.txt
tiwen_de_zhihui-2024.3.2.0.dist-info/top_level.txt
tiwen_de_zhihui-2024.3.2.0.dist-info/RECORD
